pyscenekit/__init__.py
pyscenekit/version.py
pyscenekit/scenekit2d/__init__.py
pyscenekit/scenekit2d/base.py
pyscenekit/scenekit2d/common.py
pyscenekit/scenekit2d/utils.py
pyscenekit/scenekit2d/camera/__init__.py
pyscenekit/scenekit2d/camera/geo_calib.py
pyscenekit/scenekit2d/camera/vp_gravity_prior.py
pyscenekit/scenekit2d/camera/vp_houghtransform_gaussiansphere.py
pyscenekit/scenekit2d/camera/modules/__init__.py
pyscenekit/scenekit2d/camera/modules/geo_calib/__init__.py
pyscenekit/scenekit2d/camera/modules/geo_calib/camera.py
pyscenekit/scenekit2d/camera/modules/geo_calib/extractor.py
pyscenekit/scenekit2d/camera/modules/geo_calib/geocalib.py
pyscenekit/scenekit2d/camera/modules/geo_calib/gravity.py
pyscenekit/scenekit2d/camera/modules/geo_calib/lm_optimizer.py
pyscenekit/scenekit2d/camera/modules/geo_calib/misc.py
pyscenekit/scenekit2d/camera/modules/geo_calib/modules.py
pyscenekit/scenekit2d/camera/modules/geo_calib/perspective_fields.py
pyscenekit/scenekit2d/camera/modules/geo_calib/utils.py
pyscenekit/scenekit2d/camera/modules/vp_estimation_prior_gravity/__init__.py
pyscenekit/scenekit2d/camera/modules/vp_estimation_prior_gravity/vp_estimation.py
pyscenekit/scenekit2d/camera/modules/vp_houghtransform_gaussiansphere/__init__.py
pyscenekit/scenekit2d/camera/modules/vp_houghtransform_gaussiansphere/box.py
pyscenekit/scenekit2d/camera/modules/vp_houghtransform_gaussiansphere/config.py
pyscenekit/scenekit2d/camera/modules/vp_houghtransform_gaussiansphere/convs.py
pyscenekit/scenekit2d/camera/modules/vp_houghtransform_gaussiansphere/dgcn.py
pyscenekit/scenekit2d/camera/modules/vp_houghtransform_gaussiansphere/hourglass_pose.py
pyscenekit/scenekit2d/camera/modules/vp_houghtransform_gaussiansphere/multiscale_radius_graph.py
pyscenekit/scenekit2d/camera/modules/vp_houghtransform_gaussiansphere/vanishing_net.py
pyscenekit/scenekit2d/camera/modules/vp_houghtransform_gaussiansphere/ht/__init__.py
pyscenekit-0.0.3.dist-info/LICENSE
pyscenekit-0.0.3.dist-info/METADATA
pyscenekit-0.0.3.dist-info/WHEEL
pyscenekit-0.0.3.dist-info/top_level.txt
pyscenekit-0.0.3.dist-info/RECORD
