Metadata-Version: 2.1
Name: pyscenekit
Version: 0.0.3
Summary: PySceneKit is an open-source Python library designed for common 2D and 3D scene processing and visualization tasks.
License: MIT License
Classifier: Development Status :: 3 - Alpha
Classifier: Programming Language :: Python
Requires-Python: >=3.9.0
License-File: LICENSE
Requires-Dist: tqdm
Requires-Dist: trimesh
Requires-Dist: numpy
Requires-Dist: colorlog
Requires-Dist: pillow
Requires-Dist: hydra-core
Requires-Dist: opencv-python-headless
Requires-Dist: natsort
